relation/__init__.py
relation/map.py
relation-1.0.3.dist-info/licenses/LICENSE
relation-1.0.3.dist-info/METADATA
relation-1.0.3.dist-info/WHEEL
relation-1.0.3.dist-info/top_level.txt
relation-1.0.3.dist-info/RECORD
