Metadata-Version: 2.4
Name: relation
Version: 1.0.3
Summary: a python module for making relationships between classes
Author-email: Phyo Thet Pai <developer@phyotp.dev>
License-Expression: MIT
Project-URL: Homepage, https://github.com/PhyoTP/Relation
License-File: LICENSE
Requires-Dist: pyvis
Dynamic: license-file
